{
  "name": "TagGroupMemberships",
  "fields": [
    {
      "fieldName": "tagId",
      "fieldType": "Long",
      "fieldValidateRules": ["required"]
    },
    {
      "fieldName": "tagGroupId",
      "fieldType": "Long",
      "fieldValidateRules": ["required"]
    }
  ],
  "relationships": [],
  "changelogDate": "20210524124739",
  "entityTableName": "tag_group_memberships",
  "dto": "mapstruct",
  "pagination": "pagination",
  "service": "serviceImpl",
  "jpaMetamodelFiltering": false,
  "fluentMethods": true,
  "readOnly": false,
  "embedded": false,
  "clientRootFolder": "",
  "applications": "*",
  "enableEntityAudit": true
}
